observ/__init__.py
observ/py.typed
observ/providers/__init__.py
observ/providers/anthropic.py
observ/providers/base.py
observ/providers/gemini.py
observ/providers/mistral.py
observ/providers/openai.py
observ/providers/openrouter.py
observ/providers/xai.py
observ_sdk-0.1.2.dist-info/METADATA
observ_sdk-0.1.2.dist-info/WHEEL
observ_sdk-0.1.2.dist-info/licenses/LICENSE
observ_sdk-0.1.2.dist-info/RECORD
