Metadata-Version: 2.4
Name: observ-sdk
Version: 0.1.2
Summary: Integration with the Observ AI platform for Python projects.
Project-URL: Homepage, https://github.com/observ-ai/observ-python
Project-URL: Repository, https://github.com/observ-ai/observ-python
Project-URL: Documentation, https://docs.observ.dev
Project-URL: Issues, https://github.com/observ-ai/observ-python/issues
Author-email: Observ <support@observ.dev>
License: MIT
License-File: LICENSE
Keywords: ai,anthropic,caching,gemini,llm,mistral,observ,observability,openai,tracing
Classifier: Development Status :: 4 - Beta
Classifier: Intended Audience :: Developers
Classifier: License :: OSI Approved :: MIT License
Classifier: Programming Language :: Python :: 3
Classifier: Programming Language :: Python :: 3.9
Classifier: Programming Language :: Python :: 3.10
Classifier: Programming Language :: Python :: 3.11
Classifier: Programming Language :: Python :: 3.12
Classifier: Programming Language :: Python :: 3.13
Classifier: Typing :: Typed
Requires-Python: >=3.9
Requires-Dist: httpx>=0.24.0
Provides-Extra: all
Requires-Dist: anthropic>=0.20.0; extra == 'all'
Requires-Dist: google-generativeai>=0.3.0; extra == 'all'
Requires-Dist: mistralai>=1.0.0; extra == 'all'
Requires-Dist: openai>=1.0.0; extra == 'all'
Provides-Extra: anthropic
Requires-Dist: anthropic>=0.20.0; extra == 'anthropic'
Provides-Extra: dev
Requires-Dist: mypy>=1.11.0; extra == 'dev'
Requires-Dist: pytest-asyncio>=0.23.0; extra == 'dev'
Requires-Dist: pytest>=8.0.0; extra == 'dev'
Requires-Dist: python-semantic-release>=9.0.0; extra == 'dev'
Requires-Dist: ruff>=0.6.0; extra == 'dev'
Provides-Extra: gemini
Requires-Dist: google-generativeai>=0.3.0; extra == 'gemini'
Provides-Extra: mistral
Requires-Dist: mistralai>=1.0.0; extra == 'mistral'
Provides-Extra: openai
Requires-Dist: openai>=1.0.0; extra == 'openai'
